[
  {
    "identifier": "iirds:Container",
    "datatype": "plus:Instance",
    "subClassOf": "plus:Objecttype",
    "rels": {},
    "label": {
      "de": "iiRDS-Container",
      "en": "iiRDS container"
    },
    "indicators": []
  },
  {
    "identifier": "iirds:iirdsDomainEntity",
    "datatype": "plus:Class",
    "subClassOf": "iirds:Root",
    "rels": {},
    "label": {
      "de": "iiRDS-Domänenentität",
      "en": "iiRDS domain Entity"
    },
    "indicators": []
  },
  {
    "identifier": "iirds:iirdsAttribute",
    "datatype": "plus:Class",
    "subClassOf": "iirds:Root",
    "rels": {},
    "label": {
      "de": "iiRDS-Attribut",
      "en": "iiRDS attribute"
    },
    "indicators": []
  },
  {
    "identifier": "iirds:InformationType",
    "datatype": "plus:Class",
    "subClassOf": "iirds:iirdsDomainEntity",
    "rels": {},
    "label": {
      "de": "Informationsart",
      "en": "Information type"
    },
    "indicators": []
  },
  {
    "identifier": "iirds:DocumentationMetadata",
    "datatype": "plus:Class",
    "subClassOf": "iirds:iirdsDomainEntity",
    "rels": {},
    "label": {
      "de": "Metadaten der Dokumentation",
      "en": "Documentation metadata"
    },
    "indicators": []
  },
  {
    "identifier": "iirds:iirdsRelationConcept",
    "datatype": "plus:Class",
    "subClassOf": "iirds:Root",
    "rels": {},
    "label": {
      "de": "iiRDS-Beziehungskonzept",
      "en": "iiRDS relation concept"
    },
    "indicators": []
  },
  {
    "identifier": "iirds:has-information-type",
    "datatype": "plus:Class",
    "subClassOf": "iirds:iirdsRelationConcept",
    "rels": {},
    "label": {
      "de": "hat Informationstyp",
      "en": "has information type"
    },
    "indicators": []
  },
  {
    "identifier": "iirds:relates-to-product-variant",
    "datatype": "plus:Relation",
    "subClassOf": "iirds:relates-to-product-metadata",
    "rels": {},
    "label": {
      "de": "bezieht sich auf Produktvariante",
      "en": "relates to product variant"
    },
    "indicators": []
  },
  {
    "identifier": "iirds:title",
    "datatype": "plus:String",
    "subClassOf": "iirds:iirdsAttribute",
    "rels": {},
    "label": {
      "de": "Titel (iiRDS)",
      "en": "Title (iIRDS)"
    },
    "indicators": []
  },
  {
    "identifier": "iirds:language",
    "datatype": "plus:Relation",
    "subClassOf": "iirds:iirdsAttribute",
    "rels": {},
    "label": {
      "de": "Sprache (iiRDS)",
      "en": "Language (iiRDS)"
    },
    "indicators": []
  },
  {
    "identifier": "iirds:ProductMetadata",
    "datatype": "plus:Class",
    "subClassOf": "iirds:DocumentationMetadata",
    "rels": {},
    "label": {
      "de": "Produktmetadaten",
      "en": "Product metadata"
    },
    "indicators": []
  },
  {
    "identifier": "iirds:Component",
    "datatype": "plus:Class",
    "subClassOf": "iirds:ProductMetadata",
    "rels": {
      "plus:has-roles": [
        "plus:AssignableMetadata"
      ],
      "plus:has-relations": [
        "iirds:relates-to-component"
      ],
      "plus:has-icons": [
        "mdi:engine"
      ]
    },
    "label": {
      "de": "Baugruppe",
      "en": "Component"
    },
    "indicators": []
  },
  {
    "identifier": "iirds:relates-to-product-metadata",
    "datatype": "plus:Relation",
    "subClassOf": "iirds:iirdsRelationConcept",
    "rels": {},
    "label": {
      "de": "bezieht sich auf Produktmetadaten",
      "en": "relates to product metadata"
    },
    "indicators": []
  },
  {
    "identifier": "iirds:relates-to-product-lifecycle-phase",
    "datatype": "plus:Relation",
    "subClassOf": "iirds:relates-to-product-metadata",
    "rels": {},
    "label": {
      "de": "bezieht sich auf Produktlebenszyklusphase",
      "en": "relates to a product lifecycle phase"
    },
    "indicators": []
  },
  {
    "identifier": "iirds:DesignAndRealization",
    "subClassOf": "iirds:ProductLifeCyclePhase",
    "datatype": "plus:Class",
    "label": {
      "de": "Produktentstehung",
      "en": "Design and realisation"
    },
    "rels": {
      "plus:has-relations": [
        "iirds:relates-to-product-lifecycle-phase"
      ]
    }
  },
  {
    "identifier": "iirds:GenericDesignAndRealization",
    "subClassOf": "iirds:DesignAndRealization",
    "datatype": "plus:Instance",
    "label": {
      "de": "Produktentstehung (generisch)",
      "en": "Design and realization (generic)"
    }
  },
  {
    "identifier": "iirds:RequirementAnalysis",
    "subClassOf": "iirds:DesignAndRealization",
    "datatype": "plus:Instance",
    "label": {
      "de": "Anforderungsanalyse",
      "en": "Requirement analysis"
    }
  },
  {
    "identifier": "iirds:Acquisition",
    "subClassOf": "iirds:DesignAndRealization",
    "datatype": "plus:Instance",
    "label": {
      "de": "Beschaffung",
      "en": "Acquisition"
    }
  },
  {
    "identifier": "iirds:Design",
    "subClassOf": "iirds:DesignAndRealization",
    "datatype": "plus:Instance",
    "label": {
      "de": "Design",
      "en": "Design"
    }
  },
  {
    "identifier": "iirds:Development",
    "subClassOf": "iirds:DesignAndRealization",
    "datatype": "plus:Instance",
    "label": {
      "de": "Entwicklung",
      "en": "Development"
    }
  },
  {
    "identifier": "iirds:Production",
    "subClassOf": "iirds:DesignAndRealization",
    "datatype": "plus:Instance",
    "label": {
      "de": "Herstellung",
      "en": "Production"
    }
  },
  {
    "identifier": "iirdsMch:Construction",
    "subClassOf": "iirds:DesignAndRealization",
    "datatype": "plus:Instance",
    "label": {
      "de": "Konstruktion",
      "en": "Construction"
    }
  },
  {
    "identifier": "iirds:PuttingToUse",
    "subClassOf": "iirds:ProductLifeCyclePhase",
    "datatype": "plus:Class",
    "label": {
      "de": "In Nutzung nehmen",
      "en": "Putting to use"
    },
    "rels": {
      "plus:has-relations": [
        "iirds:relates-to-product-lifecycle-phase"
      ]
    }
  },
  {
    "identifier": "iirds:GenericPuttingToUse",
    "subClassOf": "iirds:PuttingToUse",
    "datatype": "plus:Instance",
    "label": {
      "de": "In Nutzung nehmen (generisch)",
      "en": "Putting to use (generic)"
    }
  },
  {
    "identifier": "iirdsSft:Deployment",
    "subClassOf": "iirds:PuttingToUse",
    "datatype": "plus:Instance",
    "label": {
      "de": "Bereitstellung",
      "en": "Deployment"
    }
  },
  {
    "identifier": "iirds:Configuration",
    "subClassOf": "iirds:PuttingToUse",
    "datatype": "plus:Instance",
    "label": {
      "de": "Einrichtung",
      "en": "Configuration"
    }
  },
  {
    "identifier": "iirdsMch:Assembly",
    "subClassOf": "iirds:PuttingToUse",
    "datatype": "plus:Instance",
    "label": {
      "de": "Einbau",
      "en": "Assembly"
    }
  },
  {
    "identifier": "iirdsMch:FirstUse",
    "subClassOf": "iirds:PuttingToUse",
    "datatype": "plus:Instance",
    "label": {
      "de": "Erstinbetriebnahme",
      "en": "FirstUse"
    }
  },
  {
    "identifier": "iirds:Installation",
    "subClassOf": "iirds:PuttingToUse",
    "datatype": "plus:Instance",
    "label": {
      "de": "Installation",
      "en": "Installation"
    }
  },
  {
    "identifier": "iirdsSft:Integration",
    "subClassOf": "iirds:PuttingToUse",
    "datatype": "plus:Instance",
    "label": {
      "de": "Integration",
      "en": "Integration"
    }
  },
  {
    "identifier": "iirdsMch:Transport",
    "subClassOf": "iirds:PuttingToUse",
    "datatype": "plus:Instance",
    "label": {
      "de": "Transport",
      "en": "Transport"
    }
  },
  {
    "identifier": "iirds:Use",
    "subClassOf": "iirds:ProductLifeCyclePhase",
    "datatype": "plus:Class",
    "label": {
      "de": "Nutzung",
      "en": "Use"
    },
    "rels": {
      "plus:has-relations": [
        "iirds:relates-to-product-lifecycle-phase"
      ]
    }
  },
  {
    "identifier": "iirds:GenericUse",
    "subClassOf": "iirds:Use",
    "datatype": "plus:Instance",
    "label": {
      "de": "Nutzung (generisch)",
      "en": "Use (generic)"
    }
  },
  {
    "identifier": "iirdsSft:Administration",
    "subClassOf": "iirds:Use",
    "datatype": "plus:Instance",
    "label": {
      "de": "Administration",
      "en": "Administration"
    }
  },
  {
    "identifier": "iirds:Decommissioning",
    "subClassOf": "iirds:Use",
    "datatype": "plus:Instance",
    "label": {
      "de": "Außerbetriebnahme",
      "en": "Decommissioning"
    }
  },
  {
    "identifier": "iirds:Operation",
    "subClassOf": "iirds:Use",
    "datatype": "plus:Instance",
    "label": {
      "de": "Betrieb",
      "en": "Operation"
    }
  },
  {
    "identifier": "iirds:Diagnostics",
    "subClassOf": "iirds:Use",
    "datatype": "plus:Instance",
    "label": {
      "de": "Fehlerdiagnose",
      "en": "Diagnostics"
    }
  },
  {
    "identifier": "iirdsMch:Commissioning",
    "subClassOf": "iirds:Use",
    "datatype": "plus:Instance",
    "label": {
      "de": "Inbetriebnahme",
      "en": "Commissioning"
    }
  },
  {
    "identifier": "iirdsSft:Customization",
    "subClassOf": "iirds:Use",
    "datatype": "plus:Instance",
    "label": {
      "de": "Kundenspezfische Anpassung",
      "en": "Customization"
    }
  },
  {
    "identifier": "iirds:EmergencyOperation",
    "subClassOf": "iirds:Use",
    "datatype": "plus:Instance",
    "label": {
      "de": "Notbetrieb",
      "en": "EmergencyOperation"
    }
  },
  {
    "identifier": "iirdsMch:Cleaning",
    "subClassOf": "iirds:Use",
    "datatype": "plus:Instance",
    "label": {
      "de": "Reinigung",
      "en": "Cleaning"
    }
  },
  {
    "identifier": "iirds:Repair",
    "subClassOf": "iirds:Use",
    "datatype": "plus:Instance",
    "label": {
      "de": "Reparatur",
      "en": "Repair"
    }
  },
  {
    "identifier": "iirds:Fault",
    "subClassOf": "iirds:Use",
    "datatype": "plus:Instance",
    "label": {
      "de": "Störung",
      "en": "Fault"
    }
  },
  {
    "identifier": "iirdsMch:Modification",
    "subClassOf": "iirds:Use",
    "datatype": "plus:Instance",
    "label": {
      "de": "Umrüstung",
      "en": "Modification"
    }
  },
  {
    "identifier": "iirdsSft:Update",
    "subClassOf": "iirds:Use",
    "datatype": "plus:Instance",
    "label": {
      "de": "Update",
      "en": "Update"
    }
  },
  {
    "identifier": "iirds:Maintenance",
    "subClassOf": "iirds:Use",
    "datatype": "plus:Instance",
    "label": {
      "de": "Wartung",
      "en": "Maintenance"
    }
  },
  {
    "identifier": "iirds:AfterUse",
    "subClassOf": "iirds:ProductLifeCyclePhase",
    "datatype": "plus:Class",
    "label": {
      "de": "Nutzungsende",
      "en": "After use"
    },
    "rels": {
      "plus:has-relations": [
        "iirds:relates-to-product-lifecycle-phase"
      ]
    }
  },
  {
    "identifier": "iirds:GenericAfterUse",
    "subClassOf": "iirds:AfterUse",
    "datatype": "plus:Instance",
    "label": {
      "de": "Nutzungsende (generisch)",
      "en": "After use (generic)"
    }
  },
  {
    "identifier": "iirdsSft:Deinstallation",
    "subClassOf": "iirds:AfterUse",
    "datatype": "plus:Instance",
    "label": {
      "de": "Deinstallation",
      "en": "Deinstallation"
    }
  },
  {
    "identifier": "iirdsMch:Disassembly",
    "subClassOf": "iirds:AfterUse",
    "datatype": "plus:Instance",
    "label": {
      "de": "Demontage",
      "en": "Disassembly"
    }
  },
  {
    "identifier": "iirds:Disposal",
    "subClassOf": "iirds:AfterUse",
    "datatype": "plus:Instance",
    "label": {
      "de": "Entsorgung",
      "en": "Disposal"
    }
  },
  {
    "identifier": "iirdsMch:Storage",
    "subClassOf": "iirds:AfterUse",
    "datatype": "plus:Instance",
    "label": {
      "de": "Lagerung",
      "en": "Storage"
    }
  },
  {
    "identifier": "iirdsMch:Reuse",
    "subClassOf": "iirds:AfterUse",
    "datatype": "plus:Instance",
    "label": {
      "de": "Recycling",
      "en": "Recycling"
    }
  },
  {
    "identifier": "iirdsMch:CloseDown",
    "subClassOf": "iirds:AfterUse",
    "datatype": "plus:Instance",
    "label": {
      "de": "Stillegung",
      "en": "CloseDown"
    }
  },
  {
    "identifier": "iirds:AdministrativeMetadata",
    "datatype": "plus:Class",
    "subClassOf": "iirds:iirdsDomainEntity",
    "rels": {},
    "label": {
      "de": "Verwaltungsmetadaten",
      "en": "Administrative metadata"
    },
    "indicators": []
  },
  {
    "identifier": "iirds:PartyRole",
    "datatype": "plus:Class",
    "subClassOf": "iirds:AdministrativeMetadata",
    "rels": {},
    "label": {
      "de": "Akteursrolle",
      "en": "Party role"
    },
    "indicators": []
  },
  {
    "identifier": "iirds:Inspector",
    "datatype": "plus:Instance",
    "subClassOf": "iirds:PartyRole",
    "rels": {},
    "label": {
      "de": "Inspekteur",
      "en": "Inspector"
    },
    "indicators": []
  },
  {
    "identifier": "iirds:Supplier",
    "datatype": "plus:Instance",
    "subClassOf": "iirds:PartyRole",
    "rels": {},
    "label": {
      "de": "Zulieferer",
      "en": "Supplier"
    },
    "indicators": []
  },
  {
    "identifier": "iirds:Author",
    "datatype": "plus:Instance",
    "subClassOf": "iirds:PartyRole",
    "rels": {},
    "label": {
      "de": "Autor",
      "en": "Author"
    },
    "indicators": []
  },
  {
    "identifier": "iirds:Contributor",
    "datatype": "plus:Instance",
    "subClassOf": "iirds:PartyRole",
    "rels": {},
    "label": {
      "de": "Mitarbeiter",
      "en": "Contributor"
    },
    "indicators": []
  },
  {
    "identifier": "iirds:DocumentType",
    "datatype": "plus:Class",
    "subClassOf": "iirds:InformationType",
    "rels": {
      "plus:has-roles": [
        "plus:RequiredMetadata",
        "plus:VisibleMetadata",
        "plus:AssignableMetadata"
      ],
      "plus:has-relations": [
        "iirds:has-document-type"
      ],
      "plus:has-icons": [
        "mdi:file-document"
      ],
      "plus:restricted-to-object-type": [
        "plus:Document"
      ]
    },
    "label": {
      "de": "Dokumentart",
      "en": "Document type"
    },
    "indicators": []
  },
  {
    "identifier": "iirds:OperatingInstructions",
    "datatype": "plus:Instance",
    "subClassOf": "iirds:DocumentType",
    "label": {
      "de": "Betriebsanleitung",
      "en": "Operating instructions"
    },
    "indicators": []
  },
  {
    "identifier": "iirds:Specification",
    "datatype": "plus:Instance",
    "subClassOf": "iirds:DocumentType",
    "label": {
      "de": "Spezifikation",
      "en": "Specification"
    },
    "indicators": []
  },
  {
    "identifier": "iirds:has-topic-type",
    "datatype": "plus:Relation",
    "subClassOf": "iirds:has-information-type",
    "rels": {},
    "label": {
      "de": "hat Topictyp",
      "en": "has topic type"
    },
    "indicators": []
  },
  {
    "identifier": "iirds:Concept",
    "datatype": "plus:Class",
    "subClassOf": "iirds:TopicType",
    "rels": {
      "plus:has-relations": [
        "iirds:has-topic-type"
      ]
    },
    "label": {
      "de": "Beschreibung",
      "en": "Concept"
    },
    "indicators": []
  },
  {
    "identifier": "iirds:GenericConcept",
    "subClassOf": "iirds:Concept",
    "datatype": "plus:Instance",
    "label": {
      "de": "Beschreibung",
      "en": "Concept"
    }
  },
  {
    "identifier": "iirds:Task",
    "datatype": "plus:Class",
    "subClassOf": "iirds:TopicType",
    "rels": {
      "plus:has-relations": [
        "iirds:has-topic-type"
      ]
    },
    "label": {
      "de": "Aufgabe",
      "en": "Task"
    },
    "indicators": []
  },
  {
    "identifier": "iirds:GenericTask",
    "subClassOf": "iirds:Task",
    "datatype": "plus:Instance",
    "label": {
      "de": "Aufgabe",
      "en": "Task"
    }
  },
  {
    "identifier": "iirds:Reference",
    "datatype": "plus:Class",
    "subClassOf": "iirds:TopicType",
    "rels": {
      "plus:has-relations": [
        "iirds:has-topic-type"
      ]
    },
    "label": {
      "de": "Referenz",
      "en": "Reference"
    },
    "indicators": []
  },
  {
    "identifier": "iirds:GenericReference",
    "subClassOf": "iirds:Reference",
    "datatype": "plus:Instance",
    "label": {
      "de": "Referenz",
      "en": "Reference"
    }
  },
  {
    "identifier": "iirds:Learning",
    "datatype": "plus:Class",
    "subClassOf": "iirds:TopicType",
    "rels": {
      "plus:has-relations": [
        "iirds:has-topic-type"
      ]
    },
    "label": {
      "de": "Lernen",
      "en": "Learning"
    },
    "indicators": []
  },
  {
    "identifier": "iirds:GenericLearning",
    "subClassOf": "iirds:Learning",
    "datatype": "plus:Instance",
    "label": {
      "de": "Lernen",
      "en": "Learning"
    }
  },
  {
    "identifier": "iirds:Form",
    "datatype": "plus:Class",
    "subClassOf": "iirds:TopicType",
    "rels": {
      "plus:has-relations": [
        "iirds:has-topic-type"
      ]
    },
    "label": {
      "de": "Formular",
      "en": "Form"
    },
    "indicators": []
  },
  {
    "identifier": "iirds:GenericForm",
    "subClassOf": "iirds:Form",
    "datatype": "plus:Instance",
    "label": {
      "de": "Formular",
      "en": "Form"
    }
  },
  {
    "identifier": "iirds:Troubleshooting",
    "datatype": "plus:Class",
    "subClassOf": "iirds:TopicType",
    "rels": {
      "plus:has-relations": [
        "iirds:has-topic-type"
      ]
    },
    "label": {
      "de": "Störungsbeseitigung",
      "en": "Troubleshooting"
    },
    "indicators": []
  },
  {
    "identifier": "iirds:GenericTroubleshooting",
    "subClassOf": "iirds:Troubleshooting",
    "datatype": "plus:Instance",
    "label": {
      "de": "Störungsbeseitigung",
      "en": "Troubleshooting"
    }
  },
  {
    "identifier": "iirds:FunctionalMetadata",
    "datatype": "plus:Class",
    "subClassOf": "iirds:DocumentationMetadata",
    "rels": {},
    "label": {
      "de": "Funktionale Metadaten",
      "en": "Functional metadata"
    },
    "indicators": []
  },
  {
    "identifier": "iirds:relates-to-functional-metadata",
    "datatype": "plus:Relation",
    "subClassOf": "iirds:iirdsRelationConcept",
    "rels": {},
    "label": {
      "de": "bezieht sich auf funktionale Metadaten",
      "en": "relates to functional metadata"
    },
    "indicators": []
  },
  {
    "identifier": "iirds:Event",
    "datatype": "plus:Class",
    "subClassOf": "iirds:FunctionalMetadata",
    "rels": {
      "plus:has-roles": [
        "plus:AssignableMetadata"
      ],
      "plus:has-relations": [
        "iirds:relates-to-event"
      ],
      "plus:has-icons": [
        "mdi:access-point"
      ]
    },
    "label": {
      "de": "Ereignis",
      "en": "Event"
    },
    "indicators": []
  },
  {
    "identifier": "iirds:relates-to-event",
    "datatype": "plus:Relation",
    "subClassOf": "iirds:relates-to-functional-metadata",
    "rels": {},
    "label": {
      "de": "bezieht sich auf Ereignis",
      "en": "relates to Event"
    },
    "indicators": []
  },
  {
    "identifier": "iirds:relates-to-supply",
    "datatype": "plus:Relation",
    "subClassOf": "iirds:relates-to-functional-metadata",
    "rels": {},
    "label": {
      "de": "bezieht sich auf Hilfsmittel",
      "en": "relates to supply"
    },
    "indicators": []
  },
  {
    "identifier": "iirds:PlanningTime",
    "datatype": "plus:Class",
    "subClassOf": "iirds:FunctionalMetadata",
    "rels": {},
    "label": {
      "de": "Planzeit",
      "en": "Planning time"
    },
    "indicators": []
  },
  {
    "identifier": "iirds:has-planning-time",
    "datatype": "plus:Relation",
    "subClassOf": "iirds:relates-to-functional-metadata",
    "rels": {},
    "label": {
      "de": "hat Planzeit",
      "en": "has planning time"
    },
    "indicators": []
  },
  {
    "identifier": "iirds:WorkingTime",
    "datatype": "plus:Class",
    "subClassOf": "iirds:PlanningTime",
    "rels": {},
    "label": {
      "de": "Arbeitszeit",
      "en": "Working time"
    },
    "indicators": []
  },
  {
    "identifier": "iirds:DownTime",
    "datatype": "plus:Class",
    "subClassOf": "iirds:PlanningTime",
    "rels": {},
    "label": {
      "de": "Stillstandzeit",
      "en": "Down time"
    },
    "indicators": []
  },
  {
    "identifier": "iirds:MaintenanceInterval",
    "datatype": "plus:Class",
    "subClassOf": "iirds:PlanningTime",
    "rels": {},
    "label": {
      "de": "Wartungsinterval",
      "en": "Maintenance interval"
    },
    "indicators": []
  },
  {
    "identifier": "iirds:Role",
    "datatype": "plus:Class",
    "subClassOf": "iirds:Qualification",
    "rels": {
      "plus:has-roles": [
        "plus:AssignableMetadata"
      ],
      "plus:has-relations": [
        "iirds:relates-to-qualification"
      ],
      "plus:has-icons": [
        "mdi:school"
      ]
    },
    "label": {
      "de": "Rolle",
      "en": "Role"
    },
    "indicators": []
  },
  {
    "identifier": "iirds:relates-to-qualification",
    "datatype": "plus:Relation",
    "subClassOf": "iirds:relates-to-functional-metadata",
    "rels": {},
    "label": {
      "de": "bezieht sich auf Qualifikation",
      "en": "relates to qualification"
    },
    "indicators": []
  },
  {
    "identifier": "iirds:SkillLevel",
    "datatype": "plus:Class",
    "subClassOf": "iirds:Qualification",
    "rels": {},
    "label": {
      "de": "Kenntnisstufe",
      "en": "Skill Level"
    },
    "indicators": []
  },
  {
    "identifier": "iirds:Qualification",
    "datatype": "plus:Class",
    "subClassOf": "iirds:FunctionalMetadata",
    "rels": {},
    "label": {
      "de": "Rolle",
      "en": "Role"
    },
    "indicators": []
  },
  {
    "identifier": "iirds:has-subject",
    "datatype": "plus:Relation",
    "subClassOf": "iirds:has-information-type",
    "rels": {},
    "label": {
      "de": "hat Informationsthema",
      "en": "has information subject"
    },
    "indicators": []
  },
  {
    "identifier": "iirds:Formality",
    "subClassOf": "iirds:InformationSubject",
    "datatype": "plus:Class",
    "label": {
      "de": "Formalität",
      "en": "Formality"
    }
  },
  {
    "identifier": "iirds:GenericFormality",
    "subClassOf": "iirds:Formality",
    "datatype": "plus:Instance",
    "label": {
      "de": "Formalität (generisch)",
      "en": "Formality (generic)"
    }
  },
  {
    "identifier": "iirds:WarrantyConditions",
    "subClassOf": "iirds:Formality",
    "datatype": "plus:Instance",
    "label": {
      "de": "Garantiebedingungen",
      "en": "Warranty conditions"
    }
  },
  {
    "identifier": "iirds:ManufacturerInformation",
    "subClassOf": "iirds:Formality",
    "datatype": "plus:Instance",
    "label": {
      "de": "Herstellerinformation",
      "en": "Manufacturer information"
    }
  },
  {
    "identifier": "iirds:ContactInformation",
    "subClassOf": "iirds:Formality",
    "datatype": "plus:Instance",
    "label": {
      "de": "Kontaktdaten",
      "en": "Contact information"
    }
  },
  {
    "identifier": "iirds:ScopeOfDelivery",
    "subClassOf": "iirds:Formality",
    "datatype": "plus:Instance",
    "label": {
      "de": "Lieferumfang",
      "en": "Scope of delivery"
    }
  },
  {
    "identifier": "iirds:LicenseTerm",
    "subClassOf": "iirds:Formality",
    "datatype": "plus:Instance",
    "label": {
      "de": "Lizenzbedingungen",
      "en": "License terms"
    }
  },
  {
    "identifier": "iirds:ProductIdentification",
    "subClassOf": "iirds:Formality",
    "datatype": "plus:Instance",
    "label": {
      "de": "Produktidentifikation",
      "en": "Product identification"
    }
  },
  {
    "identifier": "iirds:ProductName",
    "subClassOf": "iirds:Formality",
    "datatype": "plus:Instance",
    "label": {
      "de": "Produktname",
      "en": "Product name"
    }
  },
  {
    "identifier": "iirds:LegalInformation",
    "subClassOf": "iirds:Formality",
    "datatype": "plus:Instance",
    "label": {
      "de": "Rechtlicher Hinweis",
      "en": "Legal information"
    }
  },
  {
    "identifier": "iirds:Functionality",
    "subClassOf": "iirds:InformationSubject",
    "datatype": "plus:Class",
    "label": {
      "de": "Funktionalität",
      "en": "Functionality"
    }
  },
  {
    "identifier": "iirds:GenericFunctionality",
    "subClassOf": "iirds:Functionality",
    "datatype": "plus:Instance",
    "label": {
      "de": "Funktionalität (generisch)",
      "en": "Functionality (generic)"
    }
  },
  {
    "identifier": "iirds:Conformity",
    "subClassOf": "iirds:InformationSubject",
    "datatype": "plus:Class",
    "label": {
      "de": "Konformität",
      "en": "Conformity"
    }
  },
  {
    "identifier": "iirds:GenericConformity",
    "subClassOf": "iirds:Conformity",
    "datatype": "plus:Instance",
    "label": {
      "de": "Konformität (generisch)",
      "en": "Conformity (generic)"
    }
  },
  {
    "identifier": "iirds:ApplicableStandards",
    "subClassOf": "iirds:Conformity",
    "datatype": "plus:Instance",
    "label": {
      "de": "Geltende Norm und Richtlinie",
      "en": "Applicable standard"
    }
  },
  {
    "identifier": "iirds:DeclarationOfConformity",
    "subClassOf": "iirds:Conformity",
    "datatype": "plus:Instance",
    "label": {
      "de": "Konformitätserklärung",
      "en": "Declaration of conformity"
    }
  },
  {
    "identifier": "iirds:RiskAssessment",
    "subClassOf": "iirds:Conformity",
    "datatype": "plus:Instance",
    "label": {
      "de": "Risikobewertung",
      "en": "Risk assessment"
    }
  },
  {
    "identifier": "iirds:TechnicalReport",
    "subClassOf": "iirds:Conformity",
    "datatype": "plus:Instance",
    "label": {
      "de": "Technischer Bericht",
      "en": "Technical report"
    }
  },
  {
    "identifier": "iirds:Process",
    "subClassOf": "iirds:InformationSubject",
    "datatype": "plus:Class",
    "label": {
      "de": "Prozess",
      "en": "Process"
    }
  },
  {
    "identifier": "iirds:GenericProcess",
    "subClassOf": "iirds:Process",
    "datatype": "plus:Instance",
    "label": {
      "de": "Prozess (generisch)",
      "en": "Process (generic)"
    }
  },
  {
    "identifier": "iirds:Collection",
    "subClassOf": "iirds:InformationSubject",
    "datatype": "plus:Class",
    "label": {
      "de": "Sammlung",
      "en": "Collection"
    }
  },
  {
    "identifier": "iirds:GenericCollection",
    "subClassOf": "iirds:Collection",
    "datatype": "plus:Instance",
    "label": {
      "de": "Sammlung (generisch)",
      "en": "Collection (generic)"
    }
  },
  {
    "identifier": "iirdsMch:ListOfSpareParts",
    "subClassOf": "iirds:Collection",
    "datatype": "plus:Instance",
    "label": {
      "de": "Ersatzteile",
      "en": "List of spare parts"
    }
  },
  {
    "identifier": "iirdsMch:ListOfLubricants",
    "subClassOf": "iirds:Collection",
    "datatype": "plus:Instance",
    "label": {
      "de": "Schmiermittelstelle",
      "en": "List of lubricants"
    }
  },
  {
    "identifier": "iirdsMch:LubricationPlan",
    "subClassOf": "iirds:Collection",
    "datatype": "plus:Instance",
    "label": {
      "de": "Schmierplan",
      "en": "Lubrication plan"
    }
  },
  {
    "identifier": "iirdsMch:PartsList",
    "subClassOf": "iirds:Collection",
    "datatype": "plus:Instance",
    "label": {
      "de": "Stückliste",
      "en": "List of parts"
    }
  },
  {
    "identifier": "iirdsMch:ListOfOperatingSupplies",
    "subClassOf": "iirds:Collection",
    "datatype": "plus:Instance",
    "label": {
      "de": "Hilfs- und Betriebsstoffe",
      "en": "List of operating supplies"
    }
  },
  {
    "identifier": "iirdsMch:MaintenancePlan",
    "subClassOf": "iirds:Collection",
    "datatype": "plus:Instance",
    "label": {
      "de": "Wartungsplan",
      "en": "Maintenance plan"
    }
  },
  {
    "identifier": "iirdsMch:ListOfTools",
    "subClassOf": "iirds:Collection",
    "datatype": "plus:Instance",
    "label": {
      "de": "Werkzeugliste",
      "en": "List of tools"
    }
  },
  {
    "identifier": "iirds:Safety",
    "subClassOf": "iirds:InformationSubject",
    "datatype": "plus:Class",
    "label": {
      "de": "Sicherheit",
      "en": "Safety"
    }
  },
  {
    "identifier": "iirds:GenericSafety",
    "subClassOf": "iirds:Safety",
    "datatype": "plus:Instance",
    "label": {
      "de": "Sicherheit (generisch)",
      "en": "Safety (generic)"
    }
  },
  {
    "identifier": "iirds:IntendedUse",
    "subClassOf": "iirds:Safety",
    "datatype": "plus:Instance",
    "label": {
      "de": "Bestimmunsgemäße Verwendung",
      "en": "Intended use"
    }
  },
  {
    "identifier": "iirds:RestrictionOnUse",
    "subClassOf": "iirds:Safety",
    "datatype": "plus:Instance",
    "label": {
      "de": "Einsatzbeschränkung",
      "en": "Restriction on use"
    }
  },
  {
    "identifier": "iirdsMch:ExplosionProtection",
    "subClassOf": "iirds:Safety",
    "datatype": "plus:Instance",
    "label": {
      "de": "Explosionsschutz",
      "en": "Explosion protection"
    }
  },
  {
    "identifier": "iirdsMch:InstallationError",
    "subClassOf": "iirds:Safety",
    "datatype": "plus:Instance",
    "label": {
      "de": "Montagefehler",
      "en": "InstallationError"
    }
  },
  {
    "identifier": "iirdsMch:SafetyEquipment",
    "subClassOf": "iirds:Safety",
    "datatype": "plus:Instance",
    "label": {
      "de": "Schutzeinrichtung",
      "en": "Safety equipment"
    }
  },
  {
    "identifier": "iirdsMch:SafetyMeasure",
    "subClassOf": "iirds:Safety",
    "datatype": "plus:Instance",
    "label": {
      "de": "Schutzmaßnahme",
      "en": "SafetyMeasure"
    }
  },
  {
    "identifier": "iirds:SafetyInstruction",
    "subClassOf": "iirds:Safety",
    "datatype": "plus:Instance",
    "label": {
      "de": "Sicherheitshinweis",
      "en": "Safety instruction"
    }
  },
  {
    "identifier": "iirdsMch:EnvironmentalProtectionInstruction",
    "subClassOf": "iirds:Safety",
    "datatype": "plus:Instance",
    "label": {
      "de": "Umweltschutzanweisung",
      "en": "Environmental protection instruction"
    }
  },
  {
    "identifier": "iirdsMch:EnvironmentalNote",
    "subClassOf": "iirds:Safety",
    "datatype": "plus:Instance",
    "label": {
      "de": "Umweltschutzhinweis",
      "en": "Environmental note"
    }
  },
  {
    "identifier": "iirds:ForeseeableMisuse",
    "subClassOf": "iirds:Safety",
    "datatype": "plus:Instance",
    "label": {
      "de": "Vorhersehbarer Fehlgebrauch",
      "en": "Foreseeable misuse"
    }
  },
  {
    "identifier": "iirds:WarningMessage",
    "subClassOf": "iirds:Safety",
    "datatype": "plus:Class",
    "label": {
      "de": "Warnhinweis",
      "en": "Warning message"
    }
  },
  {
    "identifier": "iirds:GenericWarningMessage",
    "subClassOf": "iirds:WarningMessage",
    "datatype": "plus:Instance",
    "label": {
      "de": "Warnhinweis (generisch)",
      "en": "Warning message (generic)"
    }
  },
  {
    "identifier": "iirds:Notice",
    "subClassOf": "iirds:WarningMessage",
    "datatype": "plus:Instance",
    "label": {
      "de": "Warnhinweis - Hinweis",
      "en": "Warning message - Notice"
    }
  },
  {
    "identifier": "iirds:Caution",
    "subClassOf": "iirds:WarningMessage",
    "datatype": "plus:Instance",
    "label": {
      "de": "Warnhinweis - Vorsicht",
      "en": "Warning message - Caution"
    }
  },
  {
    "identifier": "iirds:Warning",
    "subClassOf": "iirds:WarningMessage",
    "datatype": "plus:Instance",
    "label": {
      "de": "Warnhinweis - Warnung",
      "en": "Warning message - Warning"
    }
  },
  {
    "identifier": "iirds:Danger",
    "subClassOf": "iirds:WarningMessage",
    "datatype": "plus:Instance",
    "label": {
      "de": "Warnhinweis - Gefahr",
      "en": "Warning message - Danger"
    }
  },
  {
    "identifier": "iirds:TechnicalData",
    "subClassOf": "iirds:InformationSubject",
    "datatype": "plus:Class",
    "label": {
      "de": "Technische Daten",
      "en": "Technical data"
    }
  },
  {
    "identifier": "iirds:GenericTechnicalData",
    "subClassOf": "iirds:TechnicalData",
    "datatype": "plus:Instance",
    "label": {
      "de": "Technische Daten (generisch)",
      "en": "Technical data (generic)"
    }
  },
  {
    "identifier": "iirdsSft:SystemRequirement",
    "subClassOf": "iirds:TechnicalData",
    "datatype": "plus:Instance",
    "label": {
      "de": "Systemanforderungen",
      "en": "System requirement (generic)"
    }
  },
  {
    "identifier": "iirds:TechnicalOverview",
    "subClassOf": "iirds:InformationSubject",
    "datatype": "plus:Class",
    "label": {
      "de": "Technische Übersicht",
      "en": "Technical overview"
    }
  },
  {
    "identifier": "iirds:GenericTechnicalOverview",
    "subClassOf": "iirds:TechnicalOverview",
    "datatype": "plus:Instance",
    "label": {
      "de": "Technische Übersicht (generisch)",
      "en": "Technical overview (generic)"
    }
  },
  {
    "identifier": "iirdsMch:Layout",
    "subClassOf": "iirds:TechnicalOverview",
    "datatype": "plus:Instance",
    "label": {
      "de": "Aufbau",
      "en": "Layout"
    }
  },
  {
    "identifier": "iirdsSft:Architecture",
    "subClassOf": "iirds:TechnicalOverview",
    "datatype": "plus:Instance",
    "label": {
      "de": "Architektur",
      "en": "Architecture"
    }
  },
  {
    "identifier": "iirds:OperatingElement",
    "subClassOf": "iirds:TechnicalOverview",
    "datatype": "plus:Instance",
    "label": {
      "de": "Bedienelemente",
      "en": "Overview control element"
    }
  },
  {
    "identifier": "iirdsMch:HydraulicDiagram",
    "subClassOf": "iirds:TechnicalOverview",
    "datatype": "plus:Instance",
    "label": {
      "de": "Hydraulikplan",
      "en": "Hydraulic diagram"
    }
  },
  {
    "identifier": "iirdsMch:PneumaticPlan",
    "subClassOf": "iirds:TechnicalOverview",
    "datatype": "plus:Instance",
    "label": {
      "de": "Pneumatikplan",
      "en": "Pneumatic plan"
    }
  },
  {
    "identifier": "iirdsMch:CircuitDiagram",
    "subClassOf": "iirds:TechnicalOverview",
    "datatype": "plus:Instance",
    "label": {
      "de": "Schaltplan",
      "en": "Circuit diagram"
    }
  },
  {
    "identifier": "iirdsSft:Interface",
    "subClassOf": "iirds:TechnicalOverview",
    "datatype": "plus:Instance",
    "label": {
      "de": "Schnittstelle",
      "en": "Interface"
    }
  },
  {
    "identifier": "iirdsMch:FlowDiagram",
    "subClassOf": "iirds:TechnicalOverview",
    "datatype": "plus:Instance",
    "label": {
      "de": "Stromlaufplan",
      "en": "Flow diagram"
    }
  },
  {
    "identifier": "iirds:OverviewSymbol",
    "subClassOf": "iirds:TechnicalOverview",
    "datatype": "plus:Instance",
    "label": {
      "de": "Symbolübersicht",
      "en": "Overview of symbols"
    }
  },
  {
    "identifier": "iirds:revision",
    "datatype": "plus:String",
    "subClassOf": "iirds:iirdsAttribute",
    "rels": {},
    "label": {
      "de": "Revision",
      "en": "Revision"
    },
    "indicators": []
  },
  {
    "identifier": "iirds:is-version-of",
    "datatype": "plus:ObjectRelation",
    "subClassOf": "iirds:iirdsRelationConcept",
    "rels": {},
    "label": {
      "de": "ist Version/Variante von",
      "en": "is version/variant of"
    },
    "indicators": []
  },
  {
    "identifier": "iirds:is-part-of-package",
    "datatype": "plus:ObjectRelation",
    "subClassOf": "iirds:iirdsRelationConcept",
    "rels": {},
    "label": {
      "de": "ist Teil von Paket",
      "en": "is part of package"
    },
    "indicators": []
  },
  {
    "identifier": "iirds:iiRDSVersion",
    "datatype": "plus:String",
    "subClassOf": "iirds:iirdsAttribute",
    "rels": {},
    "label": {
      "de": "iiRDS-Version",
      "en": "iiRDS version"
    },
    "indicators": []
  },
  {
    "identifier": "iirds:Package",
    "datatype": "plus:Class",
    "subClassOf": "iirds:InformationUnit",
    "rels": {},
    "label": {
      "de": "iiRDS-Paket",
      "en": "iiRDS package"
    },
    "indicators": []
  },
  {
    "identifier": "iirds:InformationObject",
    "datatype": "plus:Class",
    "subClassOf": "iirds:iirdsDomainEntity",
    "rels": {},
    "label": {
      "de": "Informationsobjekt",
      "en": "Information object"
    },
    "indicators": []
  },
  {
    "identifier": "iirds:InformationUnit",
    "datatype": "plus:Class",
    "subClassOf": "iirds:iirdsDomainEntity",
    "rels": {},
    "label": {
      "de": "Informationseinheit",
      "en": "Information unit"
    },
    "indicators": []
  },
  {
    "identifier": "iirds:ProductFeature",
    "datatype": "plus:Class",
    "subClassOf": "iirds:ProductMetadata",
    "rels": {
      "plus:has-roles": [
        "plus:AssignableMetadata"
      ],
      "plus:has-relations": [
        "iirds:relates-to-product-feature"
      ],
      "plus:has-icons": [
        "mdi:star-circle-outline"
      ]
    },
    "label": {
      "de": "Produktmerkmal",
      "en": "Product feature"
    },
    "indicators": []
  },
  {
    "identifier": "iirds:relates-to-product-feature",
    "datatype": "plus:Relation",
    "subClassOf": "iirds:relates-to-product-metadata",
    "rels": {},
    "label": {
      "de": "bezieht sich auf Produktmerkmal",
      "en": "relates to a product feature"
    },
    "indicators": []
  },
  {
    "identifier": "iirds:ProductProperty",
    "datatype": "plus:Class",
    "subClassOf": "iirds:ProductFeature",
    "rels": {},
    "label": {
      "de": "Produkteigenschaft",
      "en": "Product property"
    },
    "indicators": []
  },
  {
    "identifier": "iirds:ProductFunction",
    "datatype": "plus:Class",
    "subClassOf": "iirds:ProductFeature",
    "rels": {},
    "label": {
      "de": "Produktfunktion",
      "en": "Product function"
    },
    "indicators": []
  },
  {
    "identifier": "iirds:fragmentselector",
    "datatype": "plus:Class",
    "subClassOf": "iirds:Root",
    "rels": {},
    "label": {
      "de": "iiRDS-Fragment",
      "en": "iiRDS fragmnet"
    },
    "indicators": []
  },
  {
    "identifier": "iirds:DirectoryNode",
    "datatype": "plus:Class",
    "subClassOf": "iirds:Root",
    "rels": {},
    "label": {
      "de": "Verzeichnisknoten",
      "en": "DirectoryNode"
    },
    "indicators": []
  },
  {
    "identifier": "iirds:has-next-sibling",
    "datatype": "plus:String",
    "subClassOf": "iirds:Root",
    "rels": {},
    "label": {
      "de": "hat Nachfolger in Verzeichnis",
      "en": "has next sibling in directory"
    },
    "indicators": []
  },
  {
    "identifier": "iirds:has-first-child",
    "datatype": "plus:String",
    "subClassOf": "iirds:Root",
    "rels": {},
    "label": {
      "de": "hat Unterknoten in Verzeichnis",
      "en": "has child node in directory"
    },
    "indicators": []
  },
  {
    "identifier": "iirds:ProductVariant",
    "datatype": "plus:Class",
    "subClassOf": "iirds:ProductMetadata",
    "rels": {
      "plus:has-roles": [
                "plus:VisibleMetadata",
                "plus:AssignableMetadata"
      ],
      "plus:has-relations": [
        "iirds:relates-to-product-variant"
      ],
      "plus:has-icons": [
        "mdi:memory"
      ]
    },
    "label": {
      "de": "Produktvariante",
      "en": "Product variant"
    },
    "indicators": []
  },
  {
    "identifier": "iirds:InformationSubject",
    "datatype": "plus:Class",
    "subClassOf": "iirds:InformationType",
    "rels": {
      "plus:has-roles": [
        "plus:VisibleMetadata",
        "plus:AssignableMetadata"
      ],
      "plus:has-relations": [
        "iirds:has-subject"
      ],
      "plus:has-icons": [
        "mdi:file-question-outline"
      ]
    },
    "label": {
      "de": "Informationsthema",
      "en": "Information subject"
    },
    "indicators": []
  },
  {
    "identifier": "iirds:MaintenanceInstructions",
    "datatype": "plus:Instance",
    "subClassOf": "iirds:DocumentType",
    "label": {
      "de": "Wartungsanleitung",
      "en": "Maintenance instructions"
    },
    "indicators": []
  },
  {
    "identifier": "iirds:is-applicable-for-document-type",
    "datatype": "plus:Relation",
    "subClassOf": "iirds:has-information-type",
    "rels": {},
    "label": {
      "de": "ist gültig für Dokumentart",
      "en": "is applicable for document type"
    },
    "indicators": []
  },
  {
    "identifier": "iirds:has-document-type",
    "datatype": "plus:Relation",
    "subClassOf": "iirds:has-information-type",
    "rels": {},
    "label": {
      "de": "hat Dokumentart",
      "en": "has document type"
    },
    "indicators": []
  },
  {
    "identifier": "iirds:SafetyInstructions",
    "datatype": "plus:Instance",
    "subClassOf": "iirds:DocumentType",
    "label": {
      "de": "Sicherheitsanleitung",
      "en": "Safety instruction"
    },
    "indicators": []
  },
  {
    "identifier": "iirds:AssemblyInstructions",
    "datatype": "plus:Instance",
    "subClassOf": "iirds:DocumentType",
    "label": {
      "de": "Montageanleitung",
      "en": "Assembly instructions"
    },
    "indicators": []
  },
  {
    "identifier": "iirds:ProductLifeCyclePhase",
    "datatype": "plus:Class",
    "subClassOf": "iirds:ProductMetadata",
    "rels": {
      "plus:has-roles": [
        "plus:VisibleMetadata",
        "plus:AssignableMetadata"
      ],
      "plus:has-relations": [
        "iirds:relates-to-product-lifecycle-phase"
      ],
      "plus:has-icons": [
        "mdi:progress-wrench"
      ]
    },
    "label": {
      "de": "Produktlebenszyklusphase",
      "en": "Phase of product lifecycle"
    },
    "indicators": []
  },
  {
    "identifier": "iirds:Supply",
    "datatype": "plus:Class",
    "subClassOf": "iirds:FunctionalMetadata",
    "rels": {
      "plus:has-roles": [
        "plus:AssignableMetadata"
      ],
      "plus:has-relations": [
        "iirds:relates-to-supply"
      ],
      "plus:has-icons": [
        "mdi:oil"
      ]
    },
    "label": {
      "de": "Hilfsmittel",
      "en": "Supply"
    },
    "indicators": []
  },
  {
    "identifier": "iirds:GenericSupply",
    "subClassOf": "iirds:Supply",
    "datatype": "plus:Instance",
    "label": {
      "de": "Hilfsmittel (generisch)",
      "en": "Supply (generic)"
    }
  },
  {
    "identifier": "iirdsMch:OperatingSupply",
    "subClassOf": "iirds:Supply",
    "datatype": "plus:Class",
    "label": {
      "de": "Betriebsstoff",
      "en": "Operating supply"
    }
  },
  {
    "identifier": "iirdsMch:GenericOperatingSupply",
    "subClassOf": "iirdsMch:OperatingSupply",
    "datatype": "plus:Instance",
    "label": {
      "de": "Betriebsstoff (generisch)",
      "en": "Operating supply (generic)"
    }
  },
  {
    "identifier": "iirdsMch:SparePart",
    "subClassOf": "iirds:Supply",
    "datatype": "plus:Class",
    "label": {
      "de": "Ersatzteil",
      "en": "SparePart"
    }
  },
  {
    "identifier": "iirdsMch:GenericSparePart",
    "subClassOf": "iirdsMch:SparePart",
    "datatype": "plus:Instance",
    "label": {
      "de": "Ersatzteil (generisch)",
      "en": "SparePart (generic)"
    }
  },
  {
    "identifier": "iirdsMch:Lubricant",
    "subClassOf": "iirds:Supply",
    "datatype": "plus:Class",
    "label": {
      "de": "Schmierstoff",
      "en": "Lubricant"
    }
  },
  {
    "identifier": "iirdsMch:GenericLubricant",
    "subClassOf": "iirdsMch:Lubricant",
    "datatype": "plus:Instance",
    "label": {
      "de": "Schmierstoff (generisch)",
      "en": "Lubricant (generic)"
    }
  },
  {
    "identifier": "iirdsMch:ConsumableSupply",
    "subClassOf": "iirds:Supply",
    "datatype": "plus:Class",
    "label": {
      "de": "Verbrauchsmaterial",
      "en": "Consumable supply"
    }
  },
  {
    "identifier": "iirdsMch:GenericConsumableSupply",
    "subClassOf": "iirdsMch:ConsumableSupply",
    "datatype": "plus:Instance",
    "label": {
      "de": "Verbrauchsmaterial (generisch)",
      "en": "Consumable supply (generic)"
    }
  },
  {
    "identifier": "iirdsMch:HardwareTool",
    "subClassOf": "iirds:Supply",
    "datatype": "plus:Class",
    "label": {
      "de": "Werkzeug",
      "en": "Hardware tool"
    }
  },
  {
    "identifier": "iirdsMch:GenericHardwareTool",
    "subClassOf": "iirdsMch:HardwareTool",
    "datatype": "plus:Instance",
    "label": {
      "de": "Werkzeug (generisch)",
      "en": "Hardware tool (generic)"
    }
  },
  {
    "identifier": "iirds:Root",
    "datatype": "plus:Class",
    "subClassOf": "plus:Root",
    "rels": {},
    "label": {
      "de": "iiRDS Metadatenmodell",
      "en": "iiRDS metadata model"
    },
    "indicators": []
  },
  {
    "identifier": "iirds:dateOfStatus",
    "datatype": "plus:Timestamp",
    "subClassOf": "iirds:iirdsAttribute",
    "rels": {},
    "label": {
      "de": "Datum des Status (iiRDS)",
      "en": "Date of status (iiRDS)"
    },
    "indicators": []
  },
  {
    "identifier": "iirds:dateOfCreation",
    "datatype": "plus:Timestamp",
    "subClassOf": "iirds:iirdsAttribute",
    "rels": {},
    "label": {
      "de": "Datum der Erstellung (iiRDS)",
      "en": "Date of creation (iiRDS)"
    },
    "indicators": []
  },
  {
    "identifier": "iirds:has-content-lifecycle-status-value",
    "datatype": "plus:Relation",
    "subClassOf": "iirds:iirdsRelationConcept",
    "rels": {},
    "label": {
      "de": "hat Content-Lebenszyklusphase (iiRDS)",
      "en": "has content lifecycle value (iiRDS)"
    },
    "indicators": []
  },
  {
    "identifier": "iirds:has-event-code",
    "datatype": "plus:Array",
    "subClassOf": "iirds:iirdsAttribute",
    "rels": {},
    "label": {
      "de": "hat Event-Codes",
      "en": "has event codes"
    },
    "indicators": []
  },
  {
    "identifier": "iirds:Fragment",
    "datatype": "plus:Instance",
    "subClassOf": "iirds:InformationUnit",
    "rels": {},
    "label": {
      "de": "iiRDS-Fragment",
      "en": "iiRDS fragment"
    },
    "indicators": []
  },
  {
    "identifier": "iirds:QuickGuide",
    "datatype": "plus:Instance",
    "subClassOf": "iirds:DocumentType",
    "label": {
      "de": "Kurzanleitung",
      "en": "Quick reference guide"
    },
    "indicators": []
  },
  {
    "identifier": "iirds:relates-to-component",
    "datatype": "plus:Relation",
    "subClassOf": "iirds:relates-to-product-metadata",
    "rels": {},
    "label": {
      "de": "bezieht sich auf Komponente",
      "en": "relates to component"
    },
    "indicators": []
  },
  {
    "identifier": "iirds:Manufacturer",
    "datatype": "plus:Instance",
    "subClassOf": "iirds:PartyRole",
    "rels": {
      "plus:has-roles": [
        "plus:MappableProperty"
      ],
      "plus:has-relations": [
        "plus:relates-to-manufacturer"
      ],
      "plus:dependent-on-relation-mapping": [
        "plus:manufactured-by"
      ],
      "plus:dependent-on-relation": [
        "iirds:relates-to-product-variant"
      ]
    },
    "label": {
      "de": "Hersteller",
      "en": "Manufacturer"
    },
    "indicators": []
  },
  {
    "identifier": "iirds:IdentificationDocument",
    "datatype": "plus:Instance",
    "subClassOf": "iirds:DocumentType",
    "label": {
      "de": "Identifikationsdokument",
      "en": "Identification document"
    },
    "indicators": []
  },
  {
    "identifier": "iirds:ElectronicIdentificationPlate",
    "datatype": "plus:Instance",
    "subClassOf": "iirds:DocumentType",
    "label": {
      "de": "Elektronisches Typenschild",
      "en": "Electronic Identification Plate"
    },
    "indicators": []
  },
  {
    "identifier": "iirds:CEDeclarationOfConformity",
    "datatype": "plus:Instance",
    "subClassOf": "iirds:DocumentType",
    "label": {
      "de": "CE-Konformitätserklärung",
      "en": "CE declaration of conformity"
    },
    "indicators": []
  },
  {
    "identifier": "iirds:TransportInstructions",
    "datatype": "plus:Instance",
    "subClassOf": "iirds:DocumentType",
    "label": {
      "de": "Transportanleitung",
      "en": "Transport instructions"
    },
    "indicators": []
  },
  {
    "identifier": "iirds:BillOfMaterials",
    "datatype": "plus:Instance",
    "subClassOf": "iirds:DocumentType",
    "label": {
      "de": "Materialliste",
      "en": "Bill of Materials"
    },
    "indicators": []
  },
  {
    "identifier": "iirds:RepairInstructions",
    "datatype": "plus:Instance",
    "subClassOf": "iirds:DocumentType",
    "label": {
      "de": "Reparaturanleitung",
      "en": "Repair instructions"
    },
    "indicators": []
  },
  {
    "identifier": "iirds:TechnicalDrawingDiagram",
    "datatype": "plus:Instance",
    "subClassOf": "iirds:DocumentType",
    "label": {
      "de": "Technische Zeichnung",
      "en": "Technical drawing/diagram"
    },
    "indicators": []
  },
  {
    "identifier": "iirds:Plan",
    "datatype": "plus:Instance",
    "subClassOf": "iirds:DocumentType",
    "label": {
      "de": "Plan",
      "en": "Plan"
    },
    "indicators": []
  },
  {
    "identifier": "iirds:AdministratorGuide",
    "datatype": "plus:Instance",
    "subClassOf": "iirds:DocumentType",
    "label": {
      "de": "Administrationsanleitung",
      "en": "Administrator guide"
    },
    "indicators": []
  },
  {
    "identifier": "iirds:SalesCatalog",
    "datatype": "plus:Instance",
    "subClassOf": "iirds:DocumentType",
    "label": {
      "de": "Verkaufskatalog",
      "en": "Sales catalog"
    },
    "indicators": []
  },
  {
    "identifier": "iirds:InstallationInstructions",
    "datatype": "plus:Instance",
    "subClassOf": "iirds:DocumentType",
    "label": {
      "de": "Installationsanleitung",
      "en": "Installation instructions"
    },
    "indicators": []
  },
  {
    "identifier": "iirds:Certificate",
    "datatype": "plus:Instance",
    "subClassOf": "iirds:DocumentType",
    "label": {
      "de": "Zertifikat",
      "en": "Certificate"
    },
    "indicators": []
  },
  {
    "identifier": "iirds:PartsCatalog",
    "datatype": "plus:Instance",
    "subClassOf": "iirds:DocumentType",
    "label": {
      "de": "Teilekatalog",
      "en": "Parts catalog"
    },
    "indicators": []
  },
  {
    "identifier": "iirds:ContractualDocument",
    "datatype": "plus:Instance",
    "subClassOf": "iirds:DocumentType",
    "label": {
      "de": "Vertragliches Dokument",
      "en": "Contractual document"
    },
    "indicators": []
  },
  {
    "identifier": "iirds:TopicType",
    "datatype": "plus:Class",
    "subClassOf": "iirds:InformationType",
    "rels": {
      "plus:has-roles": [
        "plus:VisibleMetadata",
        "plus:AssignableMetadata"
      ],
      "plus:has-relations": [
        "iirds:has-topic-type"
      ],
      "plus:has-icons": [
        "mdi:layers"
      ],
      "plus:restricted-to-object-type": [
        "plus:Component"
      ]
    },
    "label": {
      "de": "Topictyp",
      "en": "Topic type"
    },
    "indicators": []
  },
  {
    "identifier": "http://iirds.tekom.de/iirds#",
    "datatype": "plus:Instance",
    "subClassOf": "plus:Namespace",
    "rels": {},
    "label": {
      "de": "iiRDS Core",
      "en": "iiRDS core"
    },
    "indicators": [
      "iirds"
    ]
  },
  {
    "identifier": "http://iirds.tekom.de/iirds/domain/machinery#",
    "datatype": "plus:Instance",
    "subClassOf": "plus:Namespace",
    "rels": {},
    "label": {
      "de": "iiRDS Maschinenbau",
      "en": "iiRDS Machinery"
    },
    "indicators": [
      "iirdsMch"
    ]
  },
  {
    "identifier": "http://www.w3.org/2006/vcard/ns#",
    "datatype": "plus:Instance",
    "subClassOf": "plus:Namespace",
    "rels": {},
    "label": {
      "de": "vCard-Namensraum",
      "en": "vCard namespace"
    },
    "indicators": [
      "vcard"
    ]
  },
  {
    "identifier": "http://iirds.tekom.de/iirds/domain/handover#",
    "datatype": "plus:Instance",
    "subClassOf": "plus:Namespace",
    "rels": {},
    "label": {
      "de": "iiRDS Handover",
      "en": "iiRDS Handover"
    },
    "indicators": [
      "iirdsHov"
    ]
  },
  {
    "identifier": "http://iirds.tekom.de/iirds/domain/software#",
    "datatype": "plus:Instance",
    "subClassOf": "plus:Namespace",
    "rels": {},
    "label": {
      "de": "iiRDS Software",
      "en": "iiRDS Software"
    },
    "indicators": [
      "iirdsSft"
    ]
  },
  {
    "identifier": "iirds:GenericAction",
    "datatype": "plus:Instance",
    "subClassOf": "iirds:Action",
    "rels": {},
    "attrs": {},
    "label": {
      "de": "Handlung (generisch)",
      "en": "Action (generic)"
    },
    "indicators": []
  },
  {
    "identifier": "iirds:Action",
    "datatype": "plus:Class",
    "subClassOf": "iirds:FunctionalMetadata",
    "rels": {
      "plus:has-roles": [
        "plus:VisibleMetadata",
        "plus:AssignableMetadata"
      ],
      "plus:has-relations": [
        "iirds:relates-to-action"
      ],
      "plus:has-icons": [
        "mdi:gesture-double-tap"
      ]
    },
    "attrs": {},
    "label": {
      "de": "Handlung",
      "en": "Action"
    },
    "indicators": []
  },
  {
    "identifier": "iirds:relates-to-action",
    "datatype": "plus:Relation",
    "subClassOf": "iirds:relates-to-functional-metadata",
    "rels": {},
    "attrs": {},
    "label": {
      "de": "bezieht sich auf Handlung",
      "en": "relates to action"
    },
    "indicators": []
  },
  {
    "identifier": "mdi:gesture-double-tap",
    "datatype": "plus:Instance",
    "subClassOf": "plus:Icon",
    "rels": {},
    "attrs": {},
    "label": "Action-Item",
    "indicators": []
  },
  {
    "identifier": "iirds:IdentityType",
    "datatype": "plus:Class",
    "subClassOf": "iirds:AdministrativeMetadata",
    "rels": {},
    "attrs": {},
    "label": {
      "de": "Identitäts-Typ",
      "en": "Identity type"
    },
    "indicators": []
  },
  {
    "identifier": "iirds:Identity",
    "datatype": "plus:Class",
    "subClassOf": "iirds:AdministrativeMetadata",
    "rels": {},
    "attrs": {},
    "label": {
      "de": "Identität",
      "en": "Identity"
    },
    "indicators": []
  },
  {
    "identifier": "iirds:IdentityDomain",
    "datatype": "plus:Class",
    "subClassOf": "iirds:AdministrativeMetadata",
    "rels": {},
    "attrs": {
      "plus:tooltipInfo": {
        "de": "Eine Identitätsdomain bezieht sich auf eine Partei, d. h. ein Unternehmen oder eine Organisation. Die Partei ist der Eigentümer oder Administrator der Domain. Die Domain muss weltweit eindeutig sein; ein Beispiel ist https://www.iirds.org.",
        "en": "An identity domain relates to a party, meaning a company or organization. The party is the owner or custodian of the domain. The domain must be unique worldwide; an example is https://www.iirds.org."
      }
    },
    "label": {
      "de": "Identitäts-Domäne",
      "en": "Identity domain"
    },
    "indicators": []
  },
  {
    "identifier": "iirds:has-identity-type",
    "datatype": "plus:Relation",
    "subClassOf": "iirds:iirdsRelationConcept",
    "rels": {},
    "attrs": {},
    "label": {
      "de": "hat Identitäts-Typ",
      "en": "has identity type"
    },
    "indicators": []
  },
  {
    "identifier": "iirds:ProductType",
    "datatype": "plus:Instance",
    "subClassOf": "iirds:IdentityType",
    "rels": {},
    "attrs": {
      "plus:tooltipInfo": {
        "de": "Beispiele für Produkttypen sind Bezeichnungen von Produktvarianten und Typ oder Modell.",
        "en": "Examples of product type are labels of product variants and type or model."
      }
    },
    "label": {
      "de": "Produkttyp",
      "en": "Product type"
    },
    "indicators": []
  },
  {
    "identifier": "iirds:GlobalTradeItemNumber",
    "datatype": "plus:Instance",
    "subClassOf": "iirds:IdentityType",
    "rels": {},
    "attrs": {},
    "label": {
      "de": "GTIN",
      "en": "GTIN"
    },
    "indicators": []
  },
  {
    "identifier": "iirds:EuropeanArticleNumber",
    "datatype": "plus:Instance",
    "subClassOf": "iirds:IdentityType",
    "rels": {},
    "attrs": {},
    "label": {
      "de": "EAN",
      "en": "EAN"
    },
    "indicators": []
  },
  {
    "identifier": "iirds:ArticleCode",
    "datatype": "plus:Instance",
    "subClassOf": "iirds:IdentityType",
    "rels": {},
    "attrs": {},
    "label": {
      "de": "Artikelcode",
      "en": "Article code"
    },
    "indicators": []
  },
  {
    "identifier": "iirds:SerialNumber",
    "datatype": "plus:Instance",
    "subClassOf": "iirds:IdentityType",
    "rels": {},
    "attrs": {
      "plus:tooltipInfo": {
        "de": "Nummer zur Identifizierung einer einzelnen Produktinstanz. Sie muss nicht global eindeutig sein, aber innerhalb eines Herstellers.",
        "en": "Number used to identify a single product instance. It does not need to be globally unique, but it must be unique within a manufacturer."
      }
    },
    "label": {
      "de": "Seriennummer",
      "en": "Serial number"
    },
    "indicators": []
  },
  {
    "identifier": "iirds:OrderCode",
    "datatype": "plus:Instance",
    "subClassOf": "iirds:IdentityType",
    "rels": {},
    "attrs": {},
    "label": {
      "de": "Bestellcode",
      "en": "Order code"
    },
    "indicators": []
  },
  {
    "identifier": "iirds:ObjectTypeURI",
    "datatype": "plus:Instance",
    "subClassOf": "iirds:IdentityType",
    "rels": {},
    "attrs": {
      "plus:tooltipInfo": {
        "de": "Eine weltweit eindeutige Nummer, die Produkte desselben Typs identifiziert, beispielsweise gemäß den Bestimmungen der Norm IEC 61406-2.",
        "en": "A globally biunique number that identifies products of the same type, for example, according to the stipulations made in IEC 61406-2."
      }
    },
    "label": {
      "de": "Objekt-URI eines Produkttyps",
      "en": "object URI  product type"
    },
    "indicators": []
  },
  {
    "identifier": "iirds:ObjectInstanceURI",
    "datatype": "plus:Instance",
    "subClassOf": "iirds:IdentityType",
    "rels": {},
    "attrs": {
      "plus:tooltipInfo": {
        "de": "Eine weltweit eindeutige Seriennummer, die eine Produktinstanz identifiziert, beispielsweise gemäß den Bestimmungen der Normen IEC 61406-1 oder IEC 61406-2. Wird manchmal auch Auto-ID genannt.",
        "en": "A globally unique serial number that identifies a product instance, for example, in accordance with the provisions of standards IEC 61406-1 or IEC 61406-2. Sometimes also called Auto-ID"
      }
    },
    "label": {
      "de": "Instanz einer Objekt-URI",
      "en": "Instance of object URI"
    },
    "indicators": []
  },
  {
    "identifier": "plus:SerialNumber",
    "datatype": "plus:Array",
    "subClassOf": "plus:Meta",
    "rels": {
      "plus:has-roles": [
        "plus:VisibleMetadata",
        "plus:AssignableMetadata",
        "plus:IdentityDomain"
      ],
      "iirds:has-identity-type": [
        "iirds:SerialNumber"
      ],
      "plus:has-icons": [
        "mdi:counter"
      ]
    },
    "attrs": {},
    "label": {
      "de": "Seriennummer",
      "en": "Serial number"
    },
    "indicators": []
  },
  {
    "identifier": "plus:Organisation",
    "datatype": "plus:Class",
    "subClassOf": "plus:Meta",
    "rels": {},
    "attrs": {
      "plus:tooltipInfo": {
        "de": "Hersteller des Produkts und Autor der Dokumentation",
        "en": "Manufacturer of the product and author of the documentation."
      }
    },
    "label": {
      "de": "Organisation",
      "en": "OrganiZation"
    },
    "indicators": []
  }
]